songui.py
songui-0.0.post1.dist-info/METADATA
songui-0.0.post1.dist-info/WHEEL
songui-0.0.post1.dist-info/top_level.txt
songui-0.0.post1.dist-info/RECORD
